README.txt
setup.cfg
setup.py
docs/HISTORY.txt
docs/INSTALL.txt
docs/LICENSE.GPL
docs/LICENSE.txt
qi/__init__.py
qi.LiveChat.egg-info/PKG-INFO
qi.LiveChat.egg-info/SOURCES.txt
qi.LiveChat.egg-info/dependency_links.txt
qi.LiveChat.egg-info/entry_points.txt
qi.LiveChat.egg-info/namespace_packages.txt
qi.LiveChat.egg-info/not-zip-safe
qi.LiveChat.egg-info/paster_plugins.txt
qi.LiveChat.egg-info/requires.txt
qi.LiveChat.egg-info/top_level.txt
qi/LiveChat/XMLRPCMessageKeeper.py
qi/LiveChat/__init__.py
qi/LiveChat/config.py
qi/LiveChat/configure.zcml
qi/LiveChat/interfaces.py
qi/LiveChat/tests.py
qi/LiveChat/browser/ILiveChatView.py
qi/LiveChat/browser/LiveChatKSS.py
qi/LiveChat/browser/LiveChatView.py
qi/LiveChat/browser/__init__.py
qi/LiveChat/browser/configure.zcml
qi/LiveChat/browser/emoticons.py
qi/LiveChat/browser/livechat_view.pt
qi/LiveChat/browser/resources/LiveChat.gif
qi/LiveChat/browser/resources/liveChat.png
qi/LiveChat/browser/resources/livechat.css
qi/LiveChat/browser/resources/livechat.kss
qi/LiveChat/browser/resources/smiley_cool.png
qi/LiveChat/browser/resources/smiley_lol.png
qi/LiveChat/browser/resources/smiley_sad.png
qi/LiveChat/browser/resources/smiley_skeptic.png
qi/LiveChat/browser/resources/smiley_smile.png
qi/LiveChat/browser/resources/smiley_surprised.png
qi/LiveChat/browser/resources/smiley_tongue.png
qi/LiveChat/browser/resources/smiley_wink.png
qi/LiveChat/content/LiveChat.py
qi/LiveChat/content/__init__.py
qi/LiveChat/kss/ILiveChatKSSCommands.py
qi/LiveChat/kss/LiveChatKSSCommands.py
qi/LiveChat/kss/__init__.py
qi/LiveChat/kss/beforeunload.js
qi/LiveChat/kss/configure.zcml
qi/LiveChat/kss/resetInput.js
qi/LiveChat/kss/resetScrollbar.js
qi/LiveChat/profiles/default/cssregistry.xml
qi/LiveChat/profiles/default/factorytool.xml
qi/LiveChat/profiles/default/kssregistry.xml
qi/LiveChat/profiles/default/metadata.xml
qi/LiveChat/profiles/default/rolemap.xml
qi/LiveChat/profiles/default/types.xml
qi/LiveChat/profiles/default/types/LiveChat.xml
qi/LiveChat/server/__init__.py
qi/LiveChat/server/xmlrpcServer.py