Metadata-Version: 1.0
Name: qi.LiveChat
Version: 0.21
Summary: A chat product for plone
Home-page: http://svn.plone.org/svn/collective/qi.LiveChat
Author: G. Gozadinos
Author-email: ggozad@qiweb.net
License: GPL
Keywords: plone chat
Platform: UNKNOWN
Classifier: Framework :: Plone
Classifier: Framework :: Zope2
Classifier: Framework :: Zope3
Classifier: Programming Language :: Python
Classifier: Topic :: Software Development :: Libraries :: Python Modules
